[{"line":2,"elements":[{"start_timestamp":"2022-11-15T19:06:11.668Z","before":[{"result":{"duration":6456567300,"status":"passed"},"match":{"location":"org.example.stepDefs.Hooks.OpenBrowser()"}}],"line":3,"name":"guest user could register with new valid data successfully","description":"","id":"f01-register-|-users-could-register-with-new-accounts;guest-user-could-register-with-new-valid-data-successfully","after":[{"result":{"duration":3333183200,"status":"passed"},"match":{"location":"org.example.stepDefs.Hooks.quitDriver()"}}],"type":"scenario","keyword":"Scenario","steps":[{"result":{"duration":1574380100,"status":"passed"},"line":4,"name":"user go to register page","match":{"location":"org.example.stepDefs.D01_registerStepDef.goRegisterPage()"},"keyword":"Given "},{"result":{"duration":707284400,"status":"passed"},"line":5,"name":"user enters new valid registration data","match":{"location":"org.example.stepDefs.D01_registerStepDef.enterValidRegDAta()"},"keyword":"When "},{"result":{"duration":1564614400,"status":"passed"},"line":6,"name":"user click register button","match":{"location":"org.example.stepDefs.D01_registerStepDef.clickRegister()"},"keyword":"And "},{"result":{"duration":72954900,"status":"passed"},"line":7,"name":"register is successful","match":{"location":"org.example.stepDefs.D01_registerStepDef.registerStatus()"},"keyword":"Then "}],"tags":[{"name":"@smoke"}]}],"name":"F01_Register | users could register with new accounts","description":"","id":"f01-register-|-users-could-register-with-new-accounts","keyword":"Feature","uri":"file:src/main/resources/features/F01_Register.feature","tags":[{"name":"@smoke","type":"Tag","location":{"line":1,"column":1}}]}]